Workbook

Sheet Instrucciones
A1: CENTRO DE CONTROL DE LA FIRMA
A3: Tablero: indicadores del negocio con semáforo frente a las metas. Cambia el 'Mes de análisis' en Parametros.
A4: Pipeline: cada prospecto y su etapa. Regla: toda oportunidad abierta tiene un próximo paso con fecha.
A5: Clientes: clientes activos, plan, valor mensual, riesgo y rentabilidad (horas del mes).
A6: Obligaciones: TODOS los vencimientos de TODOS los clientes. Cárgalos cada año desde el calendario oficial DIAN/municipal.
A7: Horas: registro diario de tiempo por cliente (base del ingreso por hora).
A8: Facturacion: facturas emitidas, pagos y cartera de la firma por edades.
A9: Parametros: planes, precios, listas desplegables y metas.
A11: Celdas en azul = datos que llenas. El resto se calcula solo. Los datos de ejemplo son ficticios: bórralos al empezar.

Sheet Tablero
A1: TABLERO DE LA FIRMA
A2: Mes de análisis: | B2: =Parametros!B1
A4: Indicador | B4: Valor | C4: Meta | D4: Estado
A5: FINANZAS
A6: Ingreso mensual recurrente (MRR) | B6: =SUMIFS(Clientes!$E$2:$E$301,Clientes!$G$2:$G$301,"Activo") | C6: =Parametros!B14 | D6: =IF(B6>=C6,"Verde",IF(B6>=C6*0.7,"Amarillo","Rojo"))
A7: Clientes activos | B7: =COUNTIFS(Clientes!$G$2:$G$301,"Activo")
A8: Ticket promedio | B8: =IFERROR(B6/B7,0)
A9: Facturado en el mes | B9: =SUMIFS(Facturacion!$E$2:$E$301,Facturacion!$C$2:$C$301,">="&Parametros!$B$1,Facturacion!$C$2:$C$301,"<"&EDATE(Parametros!$B$1,1))
A10: Cartera total por cobrar | B10: =SUM(Facturacion!$H$2:$H$301)
A11: Cartera con más de 30 días de mora | B11: =SUMIFS(Facturacion!$H$2:$H$301,Facturacion!$I$2:$I$301,">30")
A12: Cartera > 30 días / MRR | B12: =IFERROR(B11/B6,0) | C12: =Parametros!B17 | D12: =IF(B12<=C12,"Verde",IF(B12<=C12*1.5+0.0001,"Amarillo","Rojo"))
A13: Horas registradas en el mes | B13: =SUMIFS(Horas!$D$2:$D$301,Horas!$E$2:$E$301,Parametros!$B$1)
A14: Ingreso por hora (MRR / horas) | B14: =IFERROR(B6/B13,0) | C14: =Parametros!B18 | D14: =IF(B14>=C14,"Verde",IF(B14>=C14*0.7,"Amarillo","Rojo"))
A15: Uso de capacidad | B15: =IFERROR(B13/Parametros!B20,0) | C15: 0.8 | D15: =IF(B15<=C15,"Verde",IF(B15<=C15*1.5+0.0001,"Amarillo","Rojo"))
A16: Concentración: cliente más grande / MRR | B16: =IFERROR(MAX(Clientes!$L$2:$L$301),0) | C16: =Parametros!B19 | D16: =IF(B16<=C16,"Verde",IF(B16<=C16*1.5+0.0001,"Amarillo","Rojo"))
A17: COMERCIAL
A18: Clientes nuevos en el mes | B18: =COUNTIFS(Clientes!$F$2:$F$301,">="&Parametros!$B$1,Clientes!$F$2:$F$301,"<"&EDATE(Parametros!$B$1,1)) | C18: =Parametros!B15 | D18: =IF(B18>=C18,"Verde",IF(B18>=C18*0.7,"Amarillo","Rojo"))
A19: Oportunidades abiertas | B19: =SUM(Pipeline!$M$2:$M$301)
A20: Valor mensual del pipeline abierto | B20: =SUMIFS(Pipeline!$H$2:$H$301,Pipeline!$M$2:$M$301,1)
A21: Tasa de cierre (ganados / cerrados) | B21: =IFERROR(COUNTIF(Pipeline!$F$2:$F$301,"7 Ganado")/(COUNTIF(Pipeline!$F$2:$F$301,"7 Ganado")+COUNTIF(Pipeline!$F$2:$F$301,"8 Perdido")),0) | C21: =Parametros!B16 | D21: =IF(B21>=C21,"Verde",IF(B21>=C21*0.7,"Amarillo","Rojo"))
A22: Oportunidades con próximo paso vencido o sin fecha | B22: =COUNTIF(Pipeline!$K$2:$K$301,"VENCIDO")+COUNTIF(Pipeline!$K$2:$K$301,"SIN FECHA") | C22: 0 | D22: =IF(B22<=C22,"Verde",IF(B22<=C22*1.5+0.0001,"Amarillo","Rojo"))
A23: OPERACIONES Y RIESGO
A24: Obligaciones VENCIDAS sin presentar | B24: =COUNTIF(Obligaciones!$H$2:$H$301,"VENCIDA") | C24: 0 | D24: =IF(B24<=C24,"Verde",IF(B24<=C24*1.5+0.0001,"Amarillo","Rojo"))
A25: Obligaciones URGENTES (≤ 5 días) | B25: =COUNTIF(Obligaciones!$H$2:$H$301,"URGENTE")
A26: Obligaciones próximas (6–15 días) | B26: =COUNTIF(Obligaciones!$H$2:$H$301,"PRÓXIMA")
A27: Clientes activos con riesgo ALTO | B27: =COUNTIFS(Clientes!$G$2:$G$301,"Activo",Clientes!$H$2:$H$301,"Alto") | C27: 0 | D27: =IF(B27<=C27,"Verde",IF(B27<=C27*1.5+0.0001,"Amarillo","Rojo"))
A28: Clientes con rentabilidad BAJA | B28: =COUNTIF(Clientes!$M$2:$M$301,"BAJA") | C28: 0 | D28: =IF(B28<=C28,"Verde",IF(B28<=C28*1.5+0.0001,"Amarillo","Rojo"))
A29: CLIENTE
A30: NPS (promotores − detractores) | B30: =IFERROR((COUNTIFS(Clientes!$G$2:$G$301,"Activo",Clientes!$I$2:$I$301,">=9")-COUNTIFS(Clientes!$G$2:$G$301,"Activo",Clientes!$I$2:$I$301,"<=6"))/COUNTIFS(Clientes!$G$2:$G$301,"Activo",Clientes!$I$2:$I$301,">=0")*100,0) | C30: 50 | D30: =IF(B30>=C30,"Verde",IF(B30>=C30*0.7,"Amarillo","Rojo"))

Sheet Parametros
A1: Mes de análisis (día 1) | B1: 46296 | D1: Plan | E1: Segmento | F1: Canal | G1: Etapa | H1: Obligación | I1: Estado obligación | J1: Actividad | K1: Estado cliente | L1: Riesgo | M1: Motivo pérdida
A2: Fecha de hoy | B2: =TODAY() | D2: Básico | E2: Pyme comercio | F2: Referido | G2: 1 Prospecto | H2: IVA | I2: Pendiente | J2: Contabilidad | K2: Activo | L2: Bajo | M2: Precio
D3: Empresa | E3: Pyme servicios | F3: Red personal | G3: 2 Contactado | H3: Retención en la fuente | I3: En preparación | J3: Tributario | K3: Suspendido | L3: Medio | M3: Ya tiene contador
A4: Plan | B4: Precio mensual | D4: Crecimiento | E4: Emprendedor digital | F4: Google | G4: 3 Diagnóstico agendado | H4: Renta PJ | I4: Enviada al cliente | J4: Nómina | K4: Retirado | L4: Alto | M4: Sin respuesta
A5: Básico | B5: 450000 | D5: CFO fraccional | E5: Persona natural | F5: WhatsApp | G5: 4 Diagnóstico entregado | H5: Renta PN | I5: Aprobada | J5: Informe / reunión | M5: No es el momento
A6: Empresa | B6: 750000 | D6: Renta PN | E6: Agro / ganadero | F6: LinkedIn | G6: 5 Propuesta enviada | H6: SIMPLE anticipo | I6: Presentada | J6: Diagnóstico | M6: Competencia
A7: Crecimiento | B7: 1100000 | D7: Proyecto | E7: Otro | F7: Alianza | G7: 6 Negociación | H7: SIMPLE anual | J7: Comercial | M7: No califica
A8: CFO fraccional | B8: 2200000 | F8: Charla / taller | G8: 7 Ganado | H8: ICA | J8: Administrativo
A9: Renta PN | B9: 250000 | F9: Pauta | G9: 8 Perdido | H9: Exógena
A10: Proyecto | B10: 0 | H10: Nómina electrónica
H11: PILA
H12: Estados financieros
A13: Meta | B13: Valor | H13: Renovación matrícula mercantil
A14: MRR meta (COP/mes) | B14: 15000000 | H14: Otra
A15: Clientes nuevos / mes | B15: 3
A16: Tasa de cierre mínima | B16: 0.3
A17: Cartera > 30 días máx. (% del MRR) | B17: 0.05
A18: Ingreso por hora mínimo | B18: 80000
A19: Concentración máx. por cliente | B19: 0.2
A20: Horas facturables disponibles / mes | B20: 140

Sheet Pipeline
A1: Fecha | B1: Prospecto | C1: Segmento | D1: Canal | E1: Contacto (tel/correo) | F1: Etapa | G1: Plan propuesto | H1: Valor mensual | I1: Próximo paso | J1: Fecha próximo paso | K1: Alerta | L1: Motivo pérdida | M1: Abierta (1/0)
A2: 46296 | B2: Ferretería El Progreso | C2: Pyme comercio | D2: Referido | E2: 300 000 0001 | F2: 5 Propuesta enviada | G2: Crecimiento | H2: =IF(G2="","",IFERROR(VLOOKUP(G2,Parametros!$A$5:$B$10,2,FALSE),0)) | I2: Llamar para resolver dudas | J2: 46315 | K2: =IF(OR(B2="",F2="7 Ganado",F2="8 Perdido"),"",IF(J2="","SIN FECHA",IF(J2<Parametros!$B$2,"VENCIDO","OK"))) | M2: =IF(AND(B2<>"",F2<>"7 Ganado",F2<>"8 Perdido"),1,0)
A3: 46297 | B3: Tienda Online Moda Sinú | C3: Emprendedor digital | D3: WhatsApp | E3: 300 000 0002 | F3: 3 Diagnóstico agendado | G3: Básico | H3: =IF(G3="","",IFERROR(VLOOKUP(G3,Parametros!$A$5:$B$10,2,FALSE),0)) | I3: Reunión de diagnóstico | J3: 46312 | K3: =IF(OR(B3="",F3="7 Ganado",F3="8 Perdido"),"",IF(J3="","SIN FECHA",IF(J3<Parametros!$B$2,"VENCIDO","OK"))) | M3: =IF(AND(B3<>"",F3<>"7 Ganado",F3<>"8 Perdido"),1,0)
A4: 46298 | B4: Transportes del Caribe SAS | C4: Pyme servicios | D4: Alianza | E4: 300 000 0003 | F4: 2 Contactado | G4: Empresa | H4: =IF(G4="","",IFERROR(VLOOKUP(G4,Parametros!$A$5:$B$10,2,FALSE),0)) | I4: Enviar mensaje de seguimiento | J4: 46305 | K4: =IF(OR(B4="",F4="7 Ganado",F4="8 Perdido"),"",IF(J4="","SIN FECHA",IF(J4<Parametros!$B$2,"VENCIDO","OK"))) | M4: =IF(AND(B4<>"",F4<>"7 Ganado",F4<>"8 Perdido"),1,0)
A5: 46285 | B5: Restaurante La Ribera | C5: Pyme servicios | D5: Red personal | E5: 300 000 0004 | F5: 7 Ganado | G5: Empresa | H5: =IF(G5="","",IFERROR(VLOOKUP(G5,Parametros!$A$5:$B$10,2,FALSE),0)) | K5: =IF(OR(B5="",F5="7 Ganado",F5="8 Perdido"),"",IF(J5="","SIN FECHA",IF(J5<Parametros!$B$2,"VENCIDO","OK"))) | M5: =IF(AND(B5<>"",F5<>"7 Ganado",F5<>"8 Perdido"),1,0)
A6: 46287 | B6: Distribuidora Andina | C6: Pyme comercio | D6: Google | E6: 300 000 0005 | F6: 8 Perdido | G6: Empresa | H6: =IF(G6="","",IFERROR(VLOOKUP(G6,Parametros!$A$5:$B$10,2,FALSE),0)) | K6: =IF(OR(B6="",F6="7 Ganado",F6="8 Perdido"),"",IF(J6="","SIN FECHA",IF(J6<Parametros!$B$2,"VENCIDO","OK"))) | L6: Precio | M6: =IF(AND(B6<>"",F6<>"7 Ganado",F6<>"8 Perdido"),1,0)
A7: 46300 | B7: Hacienda Los Robles | C7: Agro / ganadero | D7: Red personal | E7: 300 000 0006 | F7: 4 Diagnóstico entregado | G7: CFO fraccional | H7: =IF(G7="","",IFERROR(VLOOKUP(G7,Parametros!$A$5:$B$10,2,FALSE),0)) | I7: Presentar propuesta | J7: 46316 | K7: =IF(OR(B7="",F7="7 Ganado",F7="8 Perdido"),"",IF(J7="","SIN FECHA",IF(J7<Parametros!$B$2,"VENCIDO","OK"))) | M7: =IF(AND(B7<>"",F7<>"7 Ganado",F7<>"8 Perdido"),1,0)
H8: =IF(G8="","",IFERROR(VLOOKUP(G8,Parametros!$A$5:$B$10,2,FALSE),0)) | K8: =IF(OR(B8="",F8="7 Ganado",F8="8 Perdido"),"",IF(J8="","SIN FECHA",IF(J8<Parametros!$B$2,"VENCIDO","OK"))) | M8: =IF(AND(B8<>"",F8<>"7 Ganado",F8<>"8 Perdido"),1,0)
H9: =IF(G9="","",IFERROR(VLOOKUP(G9,Parametros!$A$5:$B$10,2,FALSE),0)) | K9: =IF(OR(B9="",F9="7 Ganado",F9="8 Perdido"),"",IF(J9="","SIN FECHA",IF(J9<Parametros!$B$2,"VENCIDO","OK"))) | M9: =IF(AND(B9<>"",F9<>"7 Ganado",F9<>"8 Perdido"),1,0)
H10: =IF(G10="","",IFERROR(VLOOKUP(G10,Parametros!$A$5:$B$10,2,FALSE),0)) | K10: =IF(OR(B10="",F10="7 Ganado",F10="8 Perdido"),"",IF(J10="","SIN FECHA",IF(J10<Parametros!$B$2,"VENCIDO","OK"))) | M10: =IF(AND(B10<>"",F10<>"7 Ganado",F10<>"8 Perdido"),1,0)
H11: =IF(G11="","",IFERROR(VLOOKUP(G11,Parametros!$A$5:$B$10,2,FALSE),0)) | K11: =IF(OR(B11="",F11="7 Ganado",F11="8 Perdido"),"",IF(J11="","SIN FECHA",IF(J11<Parametros!$B$2,"VENCIDO","OK"))) | M11: =IF(AND(B11<>"",F11<>"7 Ganado",F11<>"8 Perdido"),1,0)
H12: =IF(G12="","",IFERROR(VLOOKUP(G12,Parametros!$A$5:$B$10,2,FALSE),0)) | K12: =IF(OR(B12="",F12="7 Ganado",F12="8 Perdido"),"",IF(J12="","SIN FECHA",IF(J12<Parametros!$B$2,"VENCIDO","OK"))) | M12: =IF(AND(B12<>"",F12<>"7 Ganado",F12<>"8 Perdido"),1,0)
H13: =IF(G13="","",IFERROR(VLOOKUP(G13,Parametros!$A$5:$B$10,2,FALSE),0)) | K13: =IF(OR(B13="",F13="7 Ganado",F13="8 Perdido"),"",IF(J13="","SIN FECHA",IF(J13<Parametros!$B$2,"VENCIDO","OK"))) | M13: =IF(AND(B13<>"",F13<>"7 Ganado",F13<>"8 Perdido"),1,0)
H14: =IF(G14="","",IFERROR(VLOOKUP(G14,Parametros!$A$5:$B$10,2,FALSE),0)) | K14: =IF(OR(B14="",F14="7 Ganado",F14="8 Perdido"),"",IF(J14="","SIN FECHA",IF(J14<Parametros!$B$2,"VENCIDO","OK"))) | M14: =IF(AND(B14<>"",F14<>"7 Ganado",F14<>"8 Perdido"),1,0)
H15: =IF(G15="","",IFERROR(VLOOKUP(G15,Parametros!$A$5:$B$10,2,FALSE),0)) | K15: =IF(OR(B15="",F15="7 Ganado",F15="8 Perdido"),"",IF(J15="","SIN FECHA",IF(J15<Parametros!$B$2,"VENCIDO","OK"))) | M15: =IF(AND(B15<>"",F15<>"7 Ganado",F15<>"8 Perdido"),1,0)
H16: =IF(G16="","",IFERROR(VLOOKUP(G16,Parametros!$A$5:$B$10,2,FALSE),0)) | K16: =IF(OR(B16="",F16="7 Ganado",F16="8 Perdido"),"",IF(J16="","SIN FECHA",IF(J16<Parametros!$B$2,"VENCIDO","OK"))) | M16: =IF(AND(B16<>"",F16<>"7 Ganado",F16<>"8 Perdido"),1,0)
H17: =IF(G17="","",IFERROR(VLOOKUP(G17,Parametros!$A$5:$B$10,2,FALSE),0)) | K17: =IF(OR(B17="",F17="7 Ganado",F17="8 Perdido"),"",IF(J17="","SIN FECHA",IF(J17<Parametros!$B$2,"VENCIDO","OK"))) | M17: =IF(AND(B17<>"",F17<>"7 Ganado",F17<>"8 Perdido"),1,0)
H18: =IF(G18="","",IFERROR(VLOOKUP(G18,Parametros!$A$5:$B$10,2,FALSE),0)) | K18: =IF(OR(B18="",F18="7 Ganado",F18="8 Perdido"),"",IF(J18="","SIN FECHA",IF(J18<Parametros!$B$2,"VENCIDO","OK"))) | M18: =IF(AND(B18<>"",F18<>"7 Ganado",F18<>"8 Perdido"),1,0)
H19: =IF(G19="","",IFERROR(VLOOKUP(G19,Parametros!$A$5:$B$10,2,FALSE),0)) | K19: =IF(OR(B19="",F19="7 Ganado",F19="8 Perdido"),"",IF(J19="","SIN FECHA",IF(J19<Parametros!$B$2,"VENCIDO","OK"))) | M19: =IF(AND(B19<>"",F19<>"7 Ganado",F19<>"8 Perdido"),1,0)
... H301: =IF(G301="","",IFERROR(VLOOKUP(G301,Parametros!$A$5:$B$10,2,FALSE),0)) | K301: =IF(OR(B301="",F301="7 Ganado",F301="8 Perdido"),"",IF(J301="","SIN FECHA",IF(J301<Parametros!$B$2,"VENCIDO","OK"))) | M301: =IF(AND(B301<>"",F301<>"7 Ganado",F301<>"8 Perdido"),1,0)

Sheet Clientes
A1: Cliente | B1: NIT / C.C. | C1: Segmento | D1: Plan | E1: Valor mensual | F1: Fecha inicio | G1: Estado | H1: Riesgo | I1: Satisfacción (NPS 0–10) | J1: Horas mes análisis | K1: Ingreso por hora | L1: % del MRR | M1: Alerta rentabilidad
A2: Restaurante La Ribera | B2: 900100200 | C2: Pyme servicios | D2: Empresa | E2: 750000 | F2: 46296 | G2: Activo | H2: Bajo | I2: 9 | J2: =IF(A2="","",SUMIFS(Horas!$D$2:$D$301,Horas!$B$2:$B$301,A2,Horas!$E$2:$E$301,Parametros!$B$1)) | K2: =IF(OR(A2="",G2<>"Activo"),"",IF(N(J2)=0,"Sin horas",E2/J2)) | L2: =IF(OR(A2="",G2<>"Activo"),"",IFERROR(E2/Tablero!$B$6,0)) | M2: =IF(NOT(ISNUMBER(K2)),"",IF(K2<Parametros!$B$18,"BAJA",IF(K2<Parametros!$B$18*1.25,"AJUSTADA","SANA")))
A3: Comercializadora Sinú SAS | B3: 900300400 | C3: Pyme comercio | D3: Crecimiento | E3: 1100000 | F3: 46204 | G3: Activo | H3: Bajo | I3: 10 | J3: =IF(A3="","",SUMIFS(Horas!$D$2:$D$301,Horas!$B$2:$B$301,A3,Horas!$E$2:$E$301,Parametros!$B$1)) | K3: =IF(OR(A3="",G3<>"Activo"),"",IF(N(J3)=0,"Sin horas",E3/J3)) | L3: =IF(OR(A3="",G3<>"Activo"),"",IFERROR(E3/Tablero!$B$6,0)) | M3: =IF(NOT(ISNUMBER(K3)),"",IF(K3<Parametros!$B$18,"BAJA",IF(K3<Parametros!$B$18*1.25,"AJUSTADA","SANA")))
A4: Juan Pérez (independiente) | B4: 1067000000 | C4: Persona natural | D4: Básico | E4: 450000 | F4: 46235 | G4: Activo | H4: Medio | I4: 7 | J4: =IF(A4="","",SUMIFS(Horas!$D$2:$D$301,Horas!$B$2:$B$301,A4,Horas!$E$2:$E$301,Parametros!$B$1)) | K4: =IF(OR(A4="",G4<>"Activo"),"",IF(N(J4)=0,"Sin horas",E4/J4)) | L4: =IF(OR(A4="",G4<>"Activo"),"",IFERROR(E4/Tablero!$B$6,0)) | M4: =IF(NOT(ISNUMBER(K4)),"",IF(K4<Parametros!$B$18,"BAJA",IF(K4<Parametros!$B$18*1.25,"AJUSTADA","SANA")))
A5: Taller Mecánico Rápido | B5: 901500600 | C5: Pyme servicios | D5: Empresa | E5: 750000 | F5: 46143 | G5: Activo | H5: Alto | I5: 5 | J5: =IF(A5="","",SUMIFS(Horas!$D$2:$D$301,Horas!$B$2:$B$301,A5,Horas!$E$2:$E$301,Parametros!$B$1)) | K5: =IF(OR(A5="",G5<>"Activo"),"",IF(N(J5)=0,"Sin horas",E5/J5)) | L5: =IF(OR(A5="",G5<>"Activo"),"",IFERROR(E5/Tablero!$B$6,0)) | M5: =IF(NOT(ISNUMBER(K5)),"",IF(K5<Parametros!$B$18,"BAJA",IF(K5<Parametros!$B$18*1.25,"AJUSTADA","SANA")))
A6: Panadería Doña Ana | B6: 901700800 | C6: Pyme comercio | D6: Básico | E6: 450000 | F6: 46082 | G6: Retirado | H6: Bajo | I6: 6 | J6: =IF(A6="","",SUMIFS(Horas!$D$2:$D$301,Horas!$B$2:$B$301,A6,Horas!$E$2:$E$301,Parametros!$B$1)) | K6: =IF(OR(A6="",G6<>"Activo"),"",IF(N(J6)=0,"Sin horas",E6/J6)) | L6: =IF(OR(A6="",G6<>"Activo"),"",IFERROR(E6/Tablero!$B$6,0)) | M6: =IF(NOT(ISNUMBER(K6)),"",IF(K6<Parametros!$B$18,"BAJA",IF(K6<Parametros!$B$18*1.25,"AJUSTADA","SANA")))
J7: =IF(A7="","",SUMIFS(Horas!$D$2:$D$301,Horas!$B$2:$B$301,A7,Horas!$E$2:$E$301,Parametros!$B$1)) | K7: =IF(OR(A7="",G7<>"Activo"),"",IF(N(J7)=0,"Sin horas",E7/J7)) | L7: =IF(OR(A7="",G7<>"Activo"),"",IFERROR(E7/Tablero!$B$6,0)) | M7: =IF(NOT(ISNUMBER(K7)),"",IF(K7<Parametros!$B$18,"BAJA",IF(K7<Parametros!$B$18*1.25,"AJUSTADA","SANA")))
J8: =IF(A8="","",SUMIFS(Horas!$D$2:$D$301,Horas!$B$2:$B$301,A8,Horas!$E$2:$E$301,Parametros!$B$1)) | K8: =IF(OR(A8="",G8<>"Activo"),"",IF(N(J8)=0,"Sin horas",E8/J8)) | L8: =IF(OR(A8="",G8<>"Activo"),"",IFERROR(E8/Tablero!$B$6,0)) | M8: =IF(NOT(ISNUMBER(K8)),"",IF(K8<Parametros!$B$18,"BAJA",IF(K8<Parametros!$B$18*1.25,"AJUSTADA","SANA")))
J9: =IF(A9="","",SUMIFS(Horas!$D$2:$D$301,Horas!$B$2:$B$301,A9,Horas!$E$2:$E$301,Parametros!$B$1)) | K9: =IF(OR(A9="",G9<>"Activo"),"",IF(N(J9)=0,"Sin horas",E9/J9)) | L9: =IF(OR(A9="",G9<>"Activo"),"",IFERROR(E9/Tablero!$B$6,0)) | M9: =IF(NOT(ISNUMBER(K9)),"",IF(K9<Parametros!$B$18,"BAJA",IF(K9<Parametros!$B$18*1.25,"AJUSTADA","SANA")))
J10: =IF(A10="","",SUMIFS(Horas!$D$2:$D$301,Horas!$B$2:$B$301,A10,Horas!$E$2:$E$301,Parametros!$B$1)) | K10: =IF(OR(A10="",G10<>"Activo"),"",IF(N(J10)=0,"Sin horas",E10/J10)) | L10: =IF(OR(A10="",G10<>"Activo"),"",IFERROR(E10/Tablero!$B$6,0)) | M10: =IF(NOT(ISNUMBER(K10)),"",IF(K10<Parametros!$B$18,"BAJA",IF(K10<Parametros!$B$18*1.25,"AJUSTADA","SANA")))
J11: =IF(A11="","",SUMIFS(Horas!$D$2:$D$301,Horas!$B$2:$B$301,A11,Horas!$E$2:$E$301,Parametros!$B$1)) | K11: =IF(OR(A11="",G11<>"Activo"),"",IF(N(J11)=0,"Sin horas",E11/J11)) | L11: =IF(OR(A11="",G11<>"Activo"),"",IFERROR(E11/Tablero!$B$6,0)) | M11: =IF(NOT(ISNUMBER(K11)),"",IF(K11<Parametros!$B$18,"BAJA",IF(K11<Parametros!$B$18*1.25,"AJUSTADA","SANA")))
J12: =IF(A12="","",SUMIFS(Horas!$D$2:$D$301,Horas!$B$2:$B$301,A12,Horas!$E$2:$E$301,Parametros!$B$1)) | K12: =IF(OR(A12="",G12<>"Activo"),"",IF(N(J12)=0,"Sin horas",E12/J12)) | L12: =IF(OR(A12="",G12<>"Activo"),"",IFERROR(E12/Tablero!$B$6,0)) | M12: =IF(NOT(ISNUMBER(K12)),"",IF(K12<Parametros!$B$18,"BAJA",IF(K12<Parametros!$B$18*1.25,"AJUSTADA","SANA")))
J13: =IF(A13="","",SUMIFS(Horas!$D$2:$D$301,Horas!$B$2:$B$301,A13,Horas!$E$2:$E$301,Parametros!$B$1)) | K13: =IF(OR(A13="",G13<>"Activo"),"",IF(N(J13)=0,"Sin horas",E13/J13)) | L13: =IF(OR(A13="",G13<>"Activo"),"",IFERROR(E13/Tablero!$B$6,0)) | M13: =IF(NOT(ISNUMBER(K13)),"",IF(K13<Parametros!$B$18,"BAJA",IF(K13<Parametros!$B$18*1.25,"AJUSTADA","SANA")))
J14: =IF(A14="","",SUMIFS(Horas!$D$2:$D$301,Horas!$B$2:$B$301,A14,Horas!$E$2:$E$301,Parametros!$B$1)) | K14: =IF(OR(A14="",G14<>"Activo"),"",IF(N(J14)=0,"Sin horas",E14/J14)) | L14: =IF(OR(A14="",G14<>"Activo"),"",IFERROR(E14/Tablero!$B$6,0)) | M14: =IF(NOT(ISNUMBER(K14)),"",IF(K14<Parametros!$B$18,"BAJA",IF(K14<Parametros!$B$18*1.25,"AJUSTADA","SANA")))
J15: =IF(A15="","",SUMIFS(Horas!$D$2:$D$301,Horas!$B$2:$B$301,A15,Horas!$E$2:$E$301,Parametros!$B$1)) | K15: =IF(OR(A15="",G15<>"Activo"),"",IF(N(J15)=0,"Sin horas",E15/J15)) | L15: =IF(OR(A15="",G15<>"Activo"),"",IFERROR(E15/Tablero!$B$6,0)) | M15: =IF(NOT(ISNUMBER(K15)),"",IF(K15<Parametros!$B$18,"BAJA",IF(K15<Parametros!$B$18*1.25,"AJUSTADA","SANA")))
J16: =IF(A16="","",SUMIFS(Horas!$D$2:$D$301,Horas!$B$2:$B$301,A16,Horas!$E$2:$E$301,Parametros!$B$1)) | K16: =IF(OR(A16="",G16<>"Activo"),"",IF(N(J16)=0,"Sin horas",E16/J16)) | L16: =IF(OR(A16="",G16<>"Activo"),"",IFERROR(E16/Tablero!$B$6,0)) | M16: =IF(NOT(ISNUMBER(K16)),"",IF(K16<Parametros!$B$18,"BAJA",IF(K16<Parametros!$B$18*1.25,"AJUSTADA","SANA")))
J17: =IF(A17="","",SUMIFS(Horas!$D$2:$D$301,Horas!$B$2:$B$301,A17,Horas!$E$2:$E$301,Parametros!$B$1)) | K17: =IF(OR(A17="",G17<>"Activo"),"",IF(N(J17)=0,"Sin horas",E17/J17)) | L17: =IF(OR(A17="",G17<>"Activo"),"",IFERROR(E17/Tablero!$B$6,0)) | M17: =IF(NOT(ISNUMBER(K17)),"",IF(K17<Parametros!$B$18,"BAJA",IF(K17<Parametros!$B$18*1.25,"AJUSTADA","SANA")))
J18: =IF(A18="","",SUMIFS(Horas!$D$2:$D$301,Horas!$B$2:$B$301,A18,Horas!$E$2:$E$301,Parametros!$B$1)) | K18: =IF(OR(A18="",G18<>"Activo"),"",IF(N(J18)=0,"Sin horas",E18/J18)) | L18: =IF(OR(A18="",G18<>"Activo"),"",IFERROR(E18/Tablero!$B$6,0)) | M18: =IF(NOT(ISNUMBER(K18)),"",IF(K18<Parametros!$B$18,"BAJA",IF(K18<Parametros!$B$18*1.25,"AJUSTADA","SANA")))
... J301: =IF(A301="","",SUMIFS(Horas!$D$2:$D$301,Horas!$B$2:$B$301,A301,Horas!$E$2:$E$301,Parametros!$B$1)) | K301: =IF(OR(A301="",G301<>"Activo"),"",IF(N(J301)=0,"Sin horas",E301/J301)) | L301: =IF(OR(A301="",G301<>"Activo"),"",IFERROR(E301/Tablero!$B$6,0)) | M301: =IF(NOT(ISNUMBER(K301)),"",IF(K301<Parametros!$B$18,"BAJA",IF(K301<Parametros!$B$18*1.25,"AJUSTADA","SANA")))

Sheet Obligaciones
A1: Cliente | B1: Obligación | C1: Periodo | D1: Fecha de vencimiento | E1: Estado | F1: Responsable | G1: Días restantes | H1: Alerta | I1: Número formulario / soporte | J1: Fechas de ejemplo calculadas a partir de la fecha de generación. Usa SIEMPRE el calendario oficial vigente (DIAN / municipio).
A2: Restaurante La Ribera | B2: Retención en la fuente | C2: Sep 2026 | D2: 46314 | E2: En preparación | F2: Titular | G2: =IF(OR(A2="",D2=""),"",IF(E2="Presentada","",D2-Parametros!$B$2)) | H2: =IF(OR(A2="",D2=""),"",IF(E2="Presentada","CUMPLIDA",IF(G2<0,"VENCIDA",IF(G2<=5,"URGENTE",IF(G2<=15,"PRÓXIMA","OK")))))
A3: Comercializadora Sinú SAS | B3: IVA | C3: Bim 4 2026 | D3: 46321 | E3: Pendiente | F3: Titular | G3: =IF(OR(A3="",D3=""),"",IF(E3="Presentada","",D3-Parametros!$B$2)) | H3: =IF(OR(A3="",D3=""),"",IF(E3="Presentada","CUMPLIDA",IF(G3<0,"VENCIDA",IF(G3<=5,"URGENTE",IF(G3<=15,"PRÓXIMA","OK")))))
A4: Comercializadora Sinú SAS | B4: Retención en la fuente | C4: Sep 2026 | D4: 46309 | E4: Presentada | F4: Titular | G4: =IF(OR(A4="",D4=""),"",IF(E4="Presentada","",D4-Parametros!$B$2)) | H4: =IF(OR(A4="",D4=""),"",IF(E4="Presentada","CUMPLIDA",IF(G4<0,"VENCIDA",IF(G4<=5,"URGENTE",IF(G4<=15,"PRÓXIMA","OK")))))
A5: Juan Pérez (independiente) | B5: Renta PN | C5: AG 2025 | D5: 46351 | E5: Pendiente | F5: Titular | G5: =IF(OR(A5="",D5=""),"",IF(E5="Presentada","",D5-Parametros!$B$2)) | H5: =IF(OR(A5="",D5=""),"",IF(E5="Presentada","CUMPLIDA",IF(G5<0,"VENCIDA",IF(G5<=5,"URGENTE",IF(G5<=15,"PRÓXIMA","OK")))))
A6: Taller Mecánico Rápido | B6: Nómina electrónica | C6: Sep 2026 | D6: 46310 | E6: Pendiente | F6: Titular | G6: =IF(OR(A6="",D6=""),"",IF(E6="Presentada","",D6-Parametros!$B$2)) | H6: =IF(OR(A6="",D6=""),"",IF(E6="Presentada","CUMPLIDA",IF(G6<0,"VENCIDA",IF(G6<=5,"URGENTE",IF(G6<=15,"PRÓXIMA","OK")))))
G7: =IF(OR(A7="",D7=""),"",IF(E7="Presentada","",D7-Parametros!$B$2)) | H7: =IF(OR(A7="",D7=""),"",IF(E7="Presentada","CUMPLIDA",IF(G7<0,"VENCIDA",IF(G7<=5,"URGENTE",IF(G7<=15,"PRÓXIMA","OK")))))
G8: =IF(OR(A8="",D8=""),"",IF(E8="Presentada","",D8-Parametros!$B$2)) | H8: =IF(OR(A8="",D8=""),"",IF(E8="Presentada","CUMPLIDA",IF(G8<0,"VENCIDA",IF(G8<=5,"URGENTE",IF(G8<=15,"PRÓXIMA","OK")))))
G9: =IF(OR(A9="",D9=""),"",IF(E9="Presentada","",D9-Parametros!$B$2)) | H9: =IF(OR(A9="",D9=""),"",IF(E9="Presentada","CUMPLIDA",IF(G9<0,"VENCIDA",IF(G9<=5,"URGENTE",IF(G9<=15,"PRÓXIMA","OK")))))
G10: =IF(OR(A10="",D10=""),"",IF(E10="Presentada","",D10-Parametros!$B$2)) | H10: =IF(OR(A10="",D10=""),"",IF(E10="Presentada","CUMPLIDA",IF(G10<0,"VENCIDA",IF(G10<=5,"URGENTE",IF(G10<=15,"PRÓXIMA","OK")))))
G11: =IF(OR(A11="",D11=""),"",IF(E11="Presentada","",D11-Parametros!$B$2)) | H11: =IF(OR(A11="",D11=""),"",IF(E11="Presentada","CUMPLIDA",IF(G11<0,"VENCIDA",IF(G11<=5,"URGENTE",IF(G11<=15,"PRÓXIMA","OK")))))
G12: =IF(OR(A12="",D12=""),"",IF(E12="Presentada","",D12-Parametros!$B$2)) | H12: =IF(OR(A12="",D12=""),"",IF(E12="Presentada","CUMPLIDA",IF(G12<0,"VENCIDA",IF(G12<=5,"URGENTE",IF(G12<=15,"PRÓXIMA","OK")))))
G13: =IF(OR(A13="",D13=""),"",IF(E13="Presentada","",D13-Parametros!$B$2)) | H13: =IF(OR(A13="",D13=""),"",IF(E13="Presentada","CUMPLIDA",IF(G13<0,"VENCIDA",IF(G13<=5,"URGENTE",IF(G13<=15,"PRÓXIMA","OK")))))
G14: =IF(OR(A14="",D14=""),"",IF(E14="Presentada","",D14-Parametros!$B$2)) | H14: =IF(OR(A14="",D14=""),"",IF(E14="Presentada","CUMPLIDA",IF(G14<0,"VENCIDA",IF(G14<=5,"URGENTE",IF(G14<=15,"PRÓXIMA","OK")))))
G15: =IF(OR(A15="",D15=""),"",IF(E15="Presentada","",D15-Parametros!$B$2)) | H15: =IF(OR(A15="",D15=""),"",IF(E15="Presentada","CUMPLIDA",IF(G15<0,"VENCIDA",IF(G15<=5,"URGENTE",IF(G15<=15,"PRÓXIMA","OK")))))
G16: =IF(OR(A16="",D16=""),"",IF(E16="Presentada","",D16-Parametros!$B$2)) | H16: =IF(OR(A16="",D16=""),"",IF(E16="Presentada","CUMPLIDA",IF(G16<0,"VENCIDA",IF(G16<=5,"URGENTE",IF(G16<=15,"PRÓXIMA","OK")))))
G17: =IF(OR(A17="",D17=""),"",IF(E17="Presentada","",D17-Parametros!$B$2)) | H17: =IF(OR(A17="",D17=""),"",IF(E17="Presentada","CUMPLIDA",IF(G17<0,"VENCIDA",IF(G17<=5,"URGENTE",IF(G17<=15,"PRÓXIMA","OK")))))
G18: =IF(OR(A18="",D18=""),"",IF(E18="Presentada","",D18-Parametros!$B$2)) | H18: =IF(OR(A18="",D18=""),"",IF(E18="Presentada","CUMPLIDA",IF(G18<0,"VENCIDA",IF(G18<=5,"URGENTE",IF(G18<=15,"PRÓXIMA","OK")))))
... G301: =IF(OR(A301="",D301=""),"",IF(E301="Presentada","",D301-Parametros!$B$2)) | H301: =IF(OR(A301="",D301=""),"",IF(E301="Presentada","CUMPLIDA",IF(G301<0,"VENCIDA",IF(G301<=5,"URGENTE",IF(G301<=15,"PRÓXIMA","OK")))))

Sheet Horas
A1: Fecha | B1: Cliente | C1: Actividad | D1: Horas | E1: Mes | F1: Nota
A2: 46297 | B2: Restaurante La Ribera | C2: Contabilidad | D2: 4 | E2: =IF(A2="","",DATE(YEAR(A2),MONTH(A2),1))
A3: 46301 | B3: Restaurante La Ribera | C3: Nómina | D3: 2 | E3: =IF(A3="","",DATE(YEAR(A3),MONTH(A3),1))
A4: 46298 | B4: Comercializadora Sinú SAS | C4: Contabilidad | D4: 6 | E4: =IF(A4="","",DATE(YEAR(A4),MONTH(A4),1))
A5: 46304 | B5: Comercializadora Sinú SAS | C5: Informe / reunión | D5: 3 | E5: =IF(A5="","",DATE(YEAR(A5),MONTH(A5),1))
A6: 46302 | B6: Juan Pérez (independiente) | C6: Tributario | D6: 2 | E6: =IF(A6="","",DATE(YEAR(A6),MONTH(A6),1))
A7: 46303 | B7: Taller Mecánico Rápido | C7: Contabilidad | D7: 7 | E7: =IF(A7="","",DATE(YEAR(A7),MONTH(A7),1))
A8: 46307 | B8: Taller Mecánico Rápido | C8: Tributario | D8: 5 | E8: =IF(A8="","",DATE(YEAR(A8),MONTH(A8),1))
A9: 46293 | B9: Restaurante La Ribera | C9: Diagnóstico | D9: 2 | E9: =IF(A9="","",DATE(YEAR(A9),MONTH(A9),1))
E10: =IF(A10="","",DATE(YEAR(A10),MONTH(A10),1))
E11: =IF(A11="","",DATE(YEAR(A11),MONTH(A11),1))
E12: =IF(A12="","",DATE(YEAR(A12),MONTH(A12),1))
E13: =IF(A13="","",DATE(YEAR(A13),MONTH(A13),1))
E14: =IF(A14="","",DATE(YEAR(A14),MONTH(A14),1))
E15: =IF(A15="","",DATE(YEAR(A15),MONTH(A15),1))
E16: =IF(A16="","",DATE(YEAR(A16),MONTH(A16),1))
E17: =IF(A17="","",DATE(YEAR(A17),MONTH(A17),1))
E18: =IF(A18="","",DATE(YEAR(A18),MONTH(A18),1))
E19: =IF(A19="","",DATE(YEAR(A19),MONTH(A19),1))
E20: =IF(A20="","",DATE(YEAR(A20),MONTH(A20),1))
E21: =IF(A21="","",DATE(YEAR(A21),MONTH(A21),1))
... E301: =IF(A301="","",DATE(YEAR(A301),MONTH(A301),1))

Sheet Facturacion
A1: N.º factura | B1: Cliente | C1: Fecha emisión | D1: Fecha límite pago | E1: Valor | F1: Pagado | G1: Fecha pago | H1: Saldo | I1: Días de mora | J1: Estado
A2: FE-001 | B2: Restaurante La Ribera | C2: 46296 | D2: =IF(C2="","",C2+4) | E2: 750000 | F2: 750000 | G2: 46298 | H2: =IF(E2="","",E2-N(F2)) | I2: =IF(OR(H2="",N(H2)<=0),0,MAX(0,Parametros!$B$2-D2)) | J2: =IF(E2="","",IF(H2<=0,"Pagada",IF(I2=0,"Al día",IF(I2<=15,"1-15",IF(I2<=30,"16-30","Más de 30")))))
A3: FE-002 | B3: Comercializadora Sinú SAS | C3: 46296 | D3: =IF(C3="","",C3+4) | E3: 1100000 | F3: 1100000 | G3: 46297 | H3: =IF(E3="","",E3-N(F3)) | I3: =IF(OR(H3="",N(H3)<=0),0,MAX(0,Parametros!$B$2-D3)) | J3: =IF(E3="","",IF(H3<=0,"Pagada",IF(I3=0,"Al día",IF(I3<=15,"1-15",IF(I3<=30,"16-30","Más de 30")))))
A4: FE-003 | B4: Juan Pérez (independiente) | C4: 46296 | D4: =IF(C4="","",C4+4) | E4: 450000 | H4: =IF(E4="","",E4-N(F4)) | I4: =IF(OR(H4="",N(H4)<=0),0,MAX(0,Parametros!$B$2-D4)) | J4: =IF(E4="","",IF(H4<=0,"Pagada",IF(I4=0,"Al día",IF(I4<=15,"1-15",IF(I4<=30,"16-30","Más de 30")))))
A5: FE-004 | B5: Taller Mecánico Rápido | C5: 46296 | D5: =IF(C5="","",C5+4) | E5: 750000 | H5: =IF(E5="","",E5-N(F5)) | I5: =IF(OR(H5="",N(H5)<=0),0,MAX(0,Parametros!$B$2-D5)) | J5: =IF(E5="","",IF(H5<=0,"Pagada",IF(I5=0,"Al día",IF(I5<=15,"1-15",IF(I5<=30,"16-30","Más de 30")))))
A6: FE-005 | B6: Taller Mecánico Rápido | C6: 46266 | D6: =IF(C6="","",C6+4) | E6: 750000 | F6: 300000 | G6: 46291 | H6: =IF(E6="","",E6-N(F6)) | I6: =IF(OR(H6="",N(H6)<=0),0,MAX(0,Parametros!$B$2-D6)) | J6: =IF(E6="","",IF(H6<=0,"Pagada",IF(I6=0,"Al día",IF(I6<=15,"1-15",IF(I6<=30,"16-30","Más de 30")))))
D7: =IF(C7="","",C7+4) | H7: =IF(E7="","",E7-N(F7)) | I7: =IF(OR(H7="",N(H7)<=0),0,MAX(0,Parametros!$B$2-D7)) | J7: =IF(E7="","",IF(H7<=0,"Pagada",IF(I7=0,"Al día",IF(I7<=15,"1-15",IF(I7<=30,"16-30","Más de 30")))))
D8: =IF(C8="","",C8+4) | H8: =IF(E8="","",E8-N(F8)) | I8: =IF(OR(H8="",N(H8)<=0),0,MAX(0,Parametros!$B$2-D8)) | J8: =IF(E8="","",IF(H8<=0,"Pagada",IF(I8=0,"Al día",IF(I8<=15,"1-15",IF(I8<=30,"16-30","Más de 30")))))
D9: =IF(C9="","",C9+4) | H9: =IF(E9="","",E9-N(F9)) | I9: =IF(OR(H9="",N(H9)<=0),0,MAX(0,Parametros!$B$2-D9)) | J9: =IF(E9="","",IF(H9<=0,"Pagada",IF(I9=0,"Al día",IF(I9<=15,"1-15",IF(I9<=30,"16-30","Más de 30")))))
D10: =IF(C10="","",C10+4) | H10: =IF(E10="","",E10-N(F10)) | I10: =IF(OR(H10="",N(H10)<=0),0,MAX(0,Parametros!$B$2-D10)) | J10: =IF(E10="","",IF(H10<=0,"Pagada",IF(I10=0,"Al día",IF(I10<=15,"1-15",IF(I10<=30,"16-30","Más de 30")))))
D11: =IF(C11="","",C11+4) | H11: =IF(E11="","",E11-N(F11)) | I11: =IF(OR(H11="",N(H11)<=0),0,MAX(0,Parametros!$B$2-D11)) | J11: =IF(E11="","",IF(H11<=0,"Pagada",IF(I11=0,"Al día",IF(I11<=15,"1-15",IF(I11<=30,"16-30","Más de 30")))))
D12: =IF(C12="","",C12+4) | H12: =IF(E12="","",E12-N(F12)) | I12: =IF(OR(H12="",N(H12)<=0),0,MAX(0,Parametros!$B$2-D12)) | J12: =IF(E12="","",IF(H12<=0,"Pagada",IF(I12=0,"Al día",IF(I12<=15,"1-15",IF(I12<=30,"16-30","Más de 30")))))
D13: =IF(C13="","",C13+4) | H13: =IF(E13="","",E13-N(F13)) | I13: =IF(OR(H13="",N(H13)<=0),0,MAX(0,Parametros!$B$2-D13)) | J13: =IF(E13="","",IF(H13<=0,"Pagada",IF(I13=0,"Al día",IF(I13<=15,"1-15",IF(I13<=30,"16-30","Más de 30")))))
D14: =IF(C14="","",C14+4) | H14: =IF(E14="","",E14-N(F14)) | I14: =IF(OR(H14="",N(H14)<=0),0,MAX(0,Parametros!$B$2-D14)) | J14: =IF(E14="","",IF(H14<=0,"Pagada",IF(I14=0,"Al día",IF(I14<=15,"1-15",IF(I14<=30,"16-30","Más de 30")))))
D15: =IF(C15="","",C15+4) | H15: =IF(E15="","",E15-N(F15)) | I15: =IF(OR(H15="",N(H15)<=0),0,MAX(0,Parametros!$B$2-D15)) | J15: =IF(E15="","",IF(H15<=0,"Pagada",IF(I15=0,"Al día",IF(I15<=15,"1-15",IF(I15<=30,"16-30","Más de 30")))))
D16: =IF(C16="","",C16+4) | H16: =IF(E16="","",E16-N(F16)) | I16: =IF(OR(H16="",N(H16)<=0),0,MAX(0,Parametros!$B$2-D16)) | J16: =IF(E16="","",IF(H16<=0,"Pagada",IF(I16=0,"Al día",IF(I16<=15,"1-15",IF(I16<=30,"16-30","Más de 30")))))
D17: =IF(C17="","",C17+4) | H17: =IF(E17="","",E17-N(F17)) | I17: =IF(OR(H17="",N(H17)<=0),0,MAX(0,Parametros!$B$2-D17)) | J17: =IF(E17="","",IF(H17<=0,"Pagada",IF(I17=0,"Al día",IF(I17<=15,"1-15",IF(I17<=30,"16-30","Más de 30")))))
D18: =IF(C18="","",C18+4) | H18: =IF(E18="","",E18-N(F18)) | I18: =IF(OR(H18="",N(H18)<=0),0,MAX(0,Parametros!$B$2-D18)) | J18: =IF(E18="","",IF(H18<=0,"Pagada",IF(I18=0,"Al día",IF(I18<=15,"1-15",IF(I18<=30,"16-30","Más de 30")))))
... D301: =IF(C301="","",C301+4) | H301: =IF(E301="","",E301-N(F301)) | I301: =IF(OR(H301="",N(H301)<=0),0,MAX(0,Parametros!$B$2-D301)) | J301: =IF(E301="","",IF(H301<=0,"Pagada",IF(I301=0,"Al día",IF(I301<=15,"1-15",IF(I301<=30,"16-30","Más de 30")))))
