Workbook

Sheet Instrucciones
A1: DIAGNÓSTICO FINANCIERO PYME
A3: 1. Llena la hoja 'Datos' (celdas en azul) con los estados financieros del último año o de los últimos 12 meses.
A4: 2. Responde el chequeo tributario (Sí / No / N/A).
A5: 3. La hoja 'Diagnostico' se genera sola: indicadores, semáforo, puntaje y acciones recomendadas. Está lista para imprimir o guardar como PDF en 1 página.
A6: 4. En 'Parametros' puedes ajustar los rangos verde/rojo según el sector del cliente.
A8: IMPORTANTE: los rangos son referencias generales, no estándares sectoriales. Ajústalos al sector y al tamaño del cliente.
A9: Herramienta de apoyo; no reemplaza el juicio profesional ni una revisión completa de la información.

Sheet Diagnostico
A1: DIAGNÓSTICO FINANCIERO
A2: ="Empresa: "&Datos!B2&" · NIT: "&Datos!B3&" · Sector: "&Datos!B4
A3: ="Periodo: "&Datos!B6&" · Régimen: "&Datos!B5&" · Fecha: "&TEXT(Datos!B7,"dd/mm/yyyy")
A5: CIFRAS CLAVE
A6: Ventas | B6: =Datos!B11
A7: Utilidad bruta | B7: =Datos!B11-Datos!B12
A8: Utilidad operacional (EBIT) | B8: =Datos!B11-Datos!B12-Datos!B13-Datos!B14
A9: Utilidad neta | B9: =Datos!B11-Datos!B12-Datos!B13-Datos!B14-Datos!B15+Datos!B16-Datos!B17
A10: Activo total | B10: =SUM(Datos!B20:B24)
A11: Pasivo total | B11: =SUM(Datos!B25:B29)
A12: Patrimonio | B12: =B10-B11
A14: Indicador | B14: Resultado | C14: Verde si | D14: Rojo si | E14: Semáforo | F14: Acción recomendada
A15: =Parametros!A2 | B15: =IFERROR(B7/Datos!B11,"N/D") | C15: =Parametros!C2 | D15: =Parametros!D2 | E15: =IF(ISNUMBER(B15),IF(Parametros!B2=1,IF(B15>=C15,"Verde",IF(B15<D15,"Rojo","Amarillo")),IF(B15<=C15,"Verde",IF(B15>D15,"Rojo","Amarillo"))),"N/D") | F15: =IF(E15="Rojo",Parametros!E2,IF(E15="Amarillo",Parametros!F2,IF(E15="Verde","Mantener.","Falta información.")))
A16: =Parametros!A3 | B16: =IFERROR(B8/Datos!B11,"N/D") | C16: =Parametros!C3 | D16: =Parametros!D3 | E16: =IF(ISNUMBER(B16),IF(Parametros!B3=1,IF(B16>=C16,"Verde",IF(B16<D16,"Rojo","Amarillo")),IF(B16<=C16,"Verde",IF(B16>D16,"Rojo","Amarillo"))),"N/D") | F16: =IF(E16="Rojo",Parametros!E3,IF(E16="Amarillo",Parametros!F3,IF(E16="Verde","Mantener.","Falta información.")))
A17: =Parametros!A4 | B17: =IFERROR(B9/Datos!B11,"N/D") | C17: =Parametros!C4 | D17: =Parametros!D4 | E17: =IF(ISNUMBER(B17),IF(Parametros!B4=1,IF(B17>=C17,"Verde",IF(B17<D17,"Rojo","Amarillo")),IF(B17<=C17,"Verde",IF(B17>D17,"Rojo","Amarillo"))),"N/D") | F17: =IF(E17="Rojo",Parametros!E4,IF(E17="Amarillo",Parametros!F4,IF(E17="Verde","Mantener.","Falta información.")))
A18: =Parametros!A5 | B18: =IFERROR(SUM(Datos!B20:B23)/SUM(Datos!B25:B28),"N/D") | C18: =Parametros!C5 | D18: =Parametros!D5 | E18: =IF(ISNUMBER(B18),IF(Parametros!B5=1,IF(B18>=C18,"Verde",IF(B18<D18,"Rojo","Amarillo")),IF(B18<=C18,"Verde",IF(B18>D18,"Rojo","Amarillo"))),"N/D") | F18: =IF(E18="Rojo",Parametros!E5,IF(E18="Amarillo",Parametros!F5,IF(E18="Verde","Mantener.","Falta información.")))
A19: =Parametros!A6 | B19: =IFERROR((SUM(Datos!B20:B23)-Datos!B22)/SUM(Datos!B25:B28),"N/D") | C19: =Parametros!C6 | D19: =Parametros!D6 | E19: =IF(ISNUMBER(B19),IF(Parametros!B6=1,IF(B19>=C19,"Verde",IF(B19<D19,"Rojo","Amarillo")),IF(B19<=C19,"Verde",IF(B19>D19,"Rojo","Amarillo"))),"N/D") | F19: =IF(E19="Rojo",Parametros!E6,IF(E19="Amarillo",Parametros!F6,IF(E19="Verde","Mantener.","Falta información.")))
A20: =Parametros!A7 | B20: =IFERROR(Datos!B21/Datos!B11*365,"N/D") | C20: =Parametros!C7 | D20: =Parametros!D7 | E20: =IF(ISNUMBER(B20),IF(Parametros!B7=1,IF(B20>=C20,"Verde",IF(B20<D20,"Rojo","Amarillo")),IF(B20<=C20,"Verde",IF(B20>D20,"Rojo","Amarillo"))),"N/D") | F20: =IF(E20="Rojo",Parametros!E7,IF(E20="Amarillo",Parametros!F7,IF(E20="Verde","Mantener.","Falta información.")))
A21: =Parametros!A8 | B21: =IFERROR(Datos!B22/Datos!B12*365,"N/D") | C21: =Parametros!C8 | D21: =Parametros!D8 | E21: =IF(ISNUMBER(B21),IF(Parametros!B8=1,IF(B21>=C21,"Verde",IF(B21<D21,"Rojo","Amarillo")),IF(B21<=C21,"Verde",IF(B21>D21,"Rojo","Amarillo"))),"N/D") | F21: =IF(E21="Rojo",Parametros!E8,IF(E21="Amarillo",Parametros!F8,IF(E21="Verde","Mantener.","Falta información.")))
A22: =Parametros!A9 | B22: =IFERROR(Datos!B25/Datos!B12*365,"N/D") | C22: =Parametros!C9 | D22: =Parametros!D9 | E22: =IF(ISNUMBER(B22),IF(Parametros!B9=1,IF(B22>=C22,"Verde",IF(B22<D22,"Rojo","Amarillo")),IF(B22<=C22,"Verde",IF(B22>D22,"Rojo","Amarillo"))),"N/D") | F22: =IF(E22="Rojo",Parametros!E9,IF(E22="Amarillo",Parametros!F9,IF(E22="Verde","Mantener.","Falta información.")))
A23: =Parametros!A10 | B23: =IFERROR(B20+B21-B22,"N/D") | C23: =Parametros!C10 | D23: =Parametros!D10 | E23: =IF(ISNUMBER(B23),IF(Parametros!B10=1,IF(B23>=C23,"Verde",IF(B23<D23,"Rojo","Amarillo")),IF(B23<=C23,"Verde",IF(B23>D23,"Rojo","Amarillo"))),"N/D") | F23: =IF(E23="Rojo",Parametros!E10,IF(E23="Amarillo",Parametros!F10,IF(E23="Verde","Mantener.","Falta información.")))
A24: =Parametros!A11 | B24: =IFERROR(B11/B10,"N/D") | C24: =Parametros!C11 | D24: =Parametros!D11 | E24: =IF(ISNUMBER(B24),IF(Parametros!B11=1,IF(B24>=C24,"Verde",IF(B24<D24,"Rojo","Amarillo")),IF(B24<=C24,"Verde",IF(B24>D24,"Rojo","Amarillo"))),"N/D") | F24: =IF(E24="Rojo",Parametros!E11,IF(E24="Amarillo",Parametros!F11,IF(E24="Verde","Mantener.","Falta información.")))
A25: =Parametros!A12 | B25: =IFERROR(B8/Datos!B15,"N/D") | C25: =Parametros!C12 | D25: =Parametros!D12 | E25: =IF(ISNUMBER(B25),IF(Parametros!B12=1,IF(B25>=C25,"Verde",IF(B25<D25,"Rojo","Amarillo")),IF(B25<=C25,"Verde",IF(B25>D25,"Rojo","Amarillo"))),"N/D") | F25: =IF(E25="Rojo",Parametros!E12,IF(E25="Amarillo",Parametros!F12,IF(E25="Verde","Mantener.","Falta información.")))
A26: =Parametros!A13 | B26: =IFERROR(Datos!B20/Datos!B31,"N/D") | C26: =Parametros!C13 | D26: =Parametros!D13 | E26: =IF(ISNUMBER(B26),IF(Parametros!B13=1,IF(B26>=C26,"Verde",IF(B26<D26,"Rojo","Amarillo")),IF(B26<=C26,"Verde",IF(B26>D26,"Rojo","Amarillo"))),"N/D") | F26: =IF(E26="Rojo",Parametros!E13,IF(E26="Amarillo",Parametros!F13,IF(E26="Verde","Mantener.","Falta información.")))
A27: =Parametros!A14 | B27: =IFERROR(COUNTIF(Datos!B34:B43,"Sí")/(COUNTIF(Datos!B34:B43,"Sí")+COUNTIF(Datos!B34:B43,"No")),"N/D") | C27: =Parametros!C14 | D27: =Parametros!D14 | E27: =IF(ISNUMBER(B27),IF(Parametros!B14=1,IF(B27>=C27,"Verde",IF(B27<D27,"Rojo","Amarillo")),IF(B27<=C27,"Verde",IF(B27>D27,"Rojo","Amarillo"))),"N/D") | F27: =IF(E27="Rojo",Parametros!E14,IF(E27="Amarillo",Parametros!F14,IF(E27="Verde","Mantener.","Falta información.")))
A29: PUNTAJE DE SALUD FINANCIERA | B29: =IFERROR((COUNTIF(E15:E27,"Verde")*2+COUNTIF(E15:E27,"Amarillo"))/((COUNTIF(E15:E27,"Verde")+COUNTIF(E15:E27,"Amarillo")+COUNTIF(E15:E27,"Rojo"))*2),0) | C29: =IF(B29>=0.75,"SALUDABLE",IF(B29>=0.5,"EN ALERTA","CRÍTICO"))
A30: Indicadores en rojo / amarillo / verde | B30: =COUNTIF(E15:E27,"Rojo")&" / "&COUNTIF(E15:E27,"Amarillo")&" / "&COUNTIF(E15:E27,"Verde")
A32: PRÓXIMO PASO RECOMENDADO
A33: =IF(COUNTIF(E15:E27,"Rojo")>=3,"Acompañamiento financiero mensual: hay "&COUNTIF(E15:E27,"Rojo")&" indicadores críticos que requieren seguimiento continuo.",IF(COUNTIF(E15:E27,"Rojo")>=1,"Plan de acción de 90 días sobre los indicadores en rojo, con revisión mensual.","Seguimiento trimestral y planeación tributaria para proteger la rentabilidad."))
A36: Diagnóstico basado en la información suministrada por el cliente, sin auditar. Rangos de referencia generales.

Sheet Datos
A1: DATOS DEL CLIENTE
A2: Empresa | B2: Comercializadora Ejemplo SAS
A3: NIT | B3: 901000000-1
A4: Sector | B4: Comercio
A5: Régimen | B5: Ordinario
A6: Periodo analizado | B6: Ene–Dic 2025
A7: Fecha del diagnóstico | B7: 46311
A8: Elaborado por | B8: Contador Público TP ____
A10: ESTADO DE RESULTADOS (periodo) | B10: Valor COP | C10: Nota
A11: Ventas netas | B11: 1200000000
A12: Costo de ventas | B12: 840000000
A13: Gastos de administración | B13: 150000000
A14: Gastos de ventas | B14: 95000000
A15: Gastos financieros (intereses) | B15: 38000000
A16: Otros ingresos (gastos) netos | B16: 0 | C16: Positivo = ingreso
A17: Impuesto de renta | B17: 25000000
A19: BALANCE (fecha de corte) | B19: Valor COP | C19: Nota
A20: Efectivo y equivalentes | B20: 35000000
A21: Cuentas por cobrar clientes | B21: 260000000
A22: Inventarios | B22: 180000000
A23: Otros activos corrientes | B23: 20000000
A24: Activos no corrientes (propiedad, planta, otros) | B24: 210000000
A25: Proveedores | B25: 95000000
A26: Obligaciones financieras corto plazo | B26: 140000000
A27: Impuestos por pagar | B27: 30000000
A28: Otros pasivos corrientes | B28: 25000000
A29: Pasivos no corrientes | B29: 120000000
A31: Gasto fijo mensual promedio (nómina, arriendo, servicios…) | B31: 22000000 | C31: Para calcular los meses de caja disponibles
A33: CHEQUEO TRIBUTARIO | B33: Sí / No / N/A | C33: Riesgo si es 'No'
A34: RUT actualizado (responsabilidades y actividad) | B34: Sí | C34: Sanciones / responsabilidades mal asignadas
A35: Facturación electrónica habilitada y emitiendo | B35: Sí | C35: Sanción por no facturar; rechazo de costos del cliente
A36: Nómina electrónica transmitida mensualmente | B36: No | C36: Costos de nómina no deducibles
A37: Documento soporte en compras a no obligados | B37: No | C37: Costos y gastos no deducibles
A38: Retenciones en la fuente declaradas y pagadas a tiempo | B38: Sí | C38: Ineficacia de la declaración + intereses
A39: IVA / impuesto al consumo declarado a tiempo | B39: Sí | C39: Sanción por extemporaneidad e intereses
A40: Renta del último año presentada | B40: Sí | C40: Omisión / emplazamiento DIAN
A41: Información exógena reportada | B41: No | C41: Sanción por no enviar información
A42: ICA / industria y comercio al día | B42: Sí | C42: Sanciones municipales
A43: Contabilidad al día (cierre mensual ≤ 30 días) | B43: No | C43: Decisiones con información atrasada

Sheet Parametros
A1: Indicador | B1: Dirección | C1: Verde si | D1: Rojo si | E1: Acción si ROJO | F1: Acción si AMARILLO
A2: Margen bruto | B2: 1 | C2: 0.35 | D2: 0.2 | E2: Revisar precios, descuentos y costo de compra; el margen no cubre la operación. | F2: Negociar con proveedores y revisar la mezcla de productos.
A3: Margen operacional | B3: 1 | C3: 0.1 | D3: 0.03 | E3: Los gastos consumen el margen: recortar gastos fijos y revisar la estructura. | F3: Controlar los gastos de administración y ventas mes a mes.
A4: Margen neto | B4: 1 | C4: 0.07 | D4: 0.02 | E4: La rentabilidad final es crítica: revisar la carga financiera y tributaria. | F4: Planeación tributaria y reducción del costo financiero.
A5: Razón corriente | B5: 1 | C5: 1.5 | D5: 1 | E5: Riesgo de iliquidez: los pasivos de corto plazo superan los activos corrientes. | F5: Mejorar el capital de trabajo: cobrar más rápido y reestructurar la deuda de corto plazo.
A6: Prueba ácida | B6: 1 | C6: 1 | D6: 0.7 | E6: Sin inventario no alcanza a cubrir las deudas de corto plazo. | F6: Reducir el inventario inmovilizado.
A7: Días de cartera | B7: -1 | C7: 45 | D7: 90 | E7: Los clientes pagan muy tarde: política de crédito, cobro y descuentos por pronto pago. | F7: Seguimiento semanal de la cartera por edades.
A8: Días de inventario | B8: -1 | C8: 60 | D8: 120 | E8: Exceso de inventario: liquidar las referencias de baja rotación. | F8: Ajustar las compras a la rotación real.
A9: Días de proveedores | B9: 1 | C9: 30 | D9: 15 | E9: Pagas demasiado rápido: negociar plazos con los proveedores. | F9: Buscar más plazo con los proveedores clave.
A10: Ciclo de caja (días) | B10: -1 | C10: 45 | D10: 90 | E10: El negocio financia a los clientes durante demasiado tiempo: actuar sobre cartera, inventario y proveedores. | F10: Monitorear el ciclo de caja mensualmente.
A11: Endeudamiento | B11: -1 | C11: 0.5 | D11: 0.7 | E11: Deuda alta: frenar el endeudamiento nuevo y reestructurar. | F11: Vigilar el nivel de deuda antes de financiar crecimiento.
A12: Cobertura de intereses | B12: 1 | C12: 3 | D12: 1.5 | E12: La utilidad operativa apenas cubre los intereses: refinanciar. | F12: Buscar tasas más bajas o prepagar la deuda cara.
A13: Meses de caja | B13: 1 | C13: 3 | D13: 1 | E13: Menos de 1 mes de caja: plan de tesorería urgente (flujo a 13 semanas). | F13: Construir una reserva de al menos 3 meses de gastos fijos.
A14: Cumplimiento tributario | B14: 1 | C14: 1 | D14: 0.8 | E14: Riesgo alto de sanciones DIAN: normalizar las obligaciones pendientes de inmediato. | F14: Corregir los puntos pendientes del chequeo tributario.
A17: Dirección: 1 = más alto es mejor · -1 = más bajo es mejor. Los rangos son referencias generales; ajústalos por sector.
